{
  "format": "custom",
  "id": "menu_navigation",
  "label": "Menu navigation",
  "repeatable": false,
  "status": true,
  "json": {
    "Main": {
      "items": {
        "type": "Group",
        "config": {
          "label": "Items",
          "repeat": true,
          "fields": {
            "link": {
              "type": "Link",
              "config": {
                "label": "Link",
                "placeholder": "",
                "select": null,
                "allowTargetBlank": false,
                "allowText": true,
                "repeat": false,
                "variants": ["Primary", "Secondary", "CTA"]
              }
            },
            "cta_text": {
              "type": "Text",
              "config": {
                "label": "Cta text",
                "placeholder": "(Optional) - only shows when type CTA"
              }
            }
          }
        }
      }
    }
  }
}
